setup.py
Server/__init__.py
Server/server.py
Server/common/__init__.py
Server/common/const.py
Server/common/decor.py
Server/common/descriptors.py
Server/common/errors.py
Server/common/metaclasses.py
Server/common/utils.py
Server/logs/__init__.py
Server/logs/client_log_config.py
Server/logs/server_log_config.py
Server/server/__init__.py
Server/server/core.py
Server/server/database/__init__.py
Server/server/database/server_database.py
Server/server/interface/__init__.py
Server/server/interface/add_user.py
Server/server/interface/config_window.py
Server/server/interface/main_window.py
Server/server/interface/remove_user.py
Server/server/interface/stat_window.py
Server/tests/__init__.py
Server/tests/test_client.py
Server/tests/test_server.py
Server/tests/test_utils.py
my_chat_server_nov.egg-info/PKG-INFO
my_chat_server_nov.egg-info/SOURCES.txt
my_chat_server_nov.egg-info/dependency_links.txt
my_chat_server_nov.egg-info/requires.txt
my_chat_server_nov.egg-info/top_level.txt