Metadata-Version: 1.0
Name: my-chat-server-nov
Version: 1.0.0
Summary: my_chat_server
Home-page: UNKNOWN
Author: Kopylov Dmitry
Author-email: kopylovdk@gmail.com
License: UNKNOWN
Platform: UNKNOWN
